pandalog/__init__.py
pandalog/logger.py
pandalog-1.0.1.dist-info/LICENSE
pandalog-1.0.1.dist-info/METADATA
pandalog-1.0.1.dist-info/WHEEL
pandalog-1.0.1.dist-info/top_level.txt
pandalog-1.0.1.dist-info/RECORD
