Metadata-Version: 2.1
Name: pandalog
Version: 1.0.1
Summary: A simple library for logging in Python
Author: Possible Panda
Classifier: Development Status :: 3 - Alpha
Classifier: Intended Audience :: Developers
Classifier: License :: OSI Approved :: MIT License
Classifier: Programming Language :: Python :: 3.12
License-File: LICENSE
